mplfig/__init__.py
mplfig/mplfig.py
mplfig-1.0.1.dist-info/METADATA
mplfig-1.0.1.dist-info/WHEEL
mplfig-1.0.1.dist-info/licenses/LICENSE
mplfig-1.0.1.dist-info/RECORD
