Metadata-Version: 2.1
Name: mplfig
Version: 1.0.1
Summary: Save and load matplotlib figures like MATLAB's .fig files!
Project-URL: Homepage, https://github.com/PaulVirally/mplfig
Project-URL: Bug Tracker, https://github.com/PaulVirally/mplfig/issues
Author-email: Paul Virally <pvirally@gmail.com>
License: MIT License
Keywords: MATLAB,figure,matplotlib,savefig
Classifier: Framework :: Matplotlib
Classifier: License :: OSI Approved :: MIT License
Classifier: Operating System :: OS Independent
Classifier: Programming Language :: Python :: 3
Requires-Python: >=3.4
Requires-Dist: dill
